Metadata-Version: 1.1
Name: pair
Version: 0.2.0
Summary: a ladder pairing/matching library
Home-page: https://github.com/knyte/pair
Author: knyte
Author-email: galactaknyte@gmail.com
License: MIT
Download-URL: https://github.com/knyte/pair/tarball/0.2.0
Keywords: ladder,pairing,matching,Munkres
Platform: UNKNOWN
Classifier: Development Status :: 3 - Alpha
Classifier: Environment :: Console
Classifier: Intended Audience :: Developers
Classifier: Intended Audience :: Other Audience
Classifier: License :: OSI Approved :: MIT License
Classifier: Programming Language :: Python
Classifier: Topic :: Games/Entertainment :: Board Games
Classifier: Topic :: Games/Entertainment :: Real Time Strategy
Classifier: Topic :: Games/Entertainment :: Turn Based Strategy
